RUpassport/RUpassport.py
RUpassport/__init__.py
RUpassport/pasport_model.pt
RUpassport-0.1.5.dist-info/METADATA
RUpassport-0.1.5.dist-info/WHEEL
RUpassport-0.1.5.dist-info/top_level.txt
RUpassport-0.1.5.dist-info/RECORD
